app/__init__.py
app/utils.py
app/utils_db.py
app/api/__init__.py
app/api/controllers.py
app/api/models.py
app/indexer/__init__.py
app/indexer/caching.py
app/indexer/controllers.py
app/indexer/detect_open.py
app/indexer/forms.py
app/indexer/htmlparser.py
app/indexer/mk_page_vector.py
app/indexer/models.py
app/indexer/neighbours.py
app/indexer/spider.py
app/orchard/__init__.py
app/orchard/controllers.py
app/orchard/mk_urls_file.py
app/pod_finder/__init__.py
app/pod_finder/controllers.py
app/pod_finder/index_pod_file.py
app/pod_finder/score_pods.py
app/pod_finder/update_pod_list.py
pears_orchard-0.0.16.dist-info/LICENSE.md
pears_orchard-0.0.16.dist-info/METADATA
pears_orchard-0.0.16.dist-info/WHEEL
pears_orchard-0.0.16.dist-info/top_level.txt
pears_orchard-0.0.16.dist-info/RECORD
