Metadata-Version: 2.1
Name: pears-orchard
Version: 0.0.16
Summary: A decentralized search engine which can be run in local machine without letting anyone know the details about your search
Home-page: https://github.com/abhijithneilabraham/PeARS-orchard
Author: Aurelie Herbelot
Author-email: aurelie.herbelot@cantab.net
License: UNKNOWN
Platform: UNKNOWN
Classifier: Programming Language :: Python :: 3
Classifier: License :: OSI Approved :: GNU Affero General Public License v3
Classifier: Operating System :: OS Independent
Requires-Python: >=3.5
